{
  "id": "085a7e19-619d-4bf4-9c33-e120d8b41e18",
  "duration": 10.88,
  "pitch": {
    "mean": 360.03,
    "max": 1500.27,
    "std": 225.86,
    "max_mean_ratio": 4.17
  },
  "energy": {
    "mean": 0.048477,
    "max": 0.142443,
    "std": 0.033135,
    "rate_of_change": 0.012747
  },
  "speech_rate": {
    "chars_per_sec": 9.56,
    "words_per_sec": 1.84,
    "segment_count": 6
  },
  "spectral_centroid": {
    "mean": 1816.99
  },
  "timeseries": {
    "frame_sec": 0.5,
    "pitch": [
      432.92,
      138.54,
      484.23,
      462.36,
      253.92,
      531.92,
      326.87,
      451.57,
      329.55,
      445.67,
      376.56,
      537.23,
      371.47,
      377.89,
      95.1,
      179.87,
      265.29,
      350.08,
      516.71,
      450.3,
      293.5,
      277.83
    ],
    "energy": [
      0.031835,
      0.014488,
      0.080074,
      0.03396,
      0.026876,
      0.058908,
      0.03033,
      0.047204,
      0.05121,
      0.048734,
      0.030803,
      0.055827,
      0.052428,
      0.051861,
      0.007176,
      0.008618,
      0.043485,
      0.068014,
      0.098104,
      0.096691,
      0.022806,
      0.064023
    ],
    "spectral_centroid": [
      1574.18,
      2093.62,
      1368.39,
      2114.58,
      1848.17,
      1638.11,
      2017.59,
      1796.96,
      1835.46,
      2404.77,
      1562.55,
      1397.27,
      1448.69,
      1691.82,
      1595.72,
      2156.54,
      1922.97,
      2775.4,
      1974.15,
      1287.11,
      1789.84,
      1676.89
    ]
  }
}