{
  "id": "1b746866-a7b0-49a8-843e-b6563eb43014",
  "duration": 14.741,
  "pitch": {
    "mean": 429.86,
    "max": 1520.22,
    "std": 289.16,
    "max_mean_ratio": 3.54
  },
  "energy": {
    "mean": 0.054877,
    "max": 0.218142,
    "std": 0.048713,
    "rate_of_change": 0.014289
  },
  "speech_rate": {
    "chars_per_sec": 13.62,
    "words_per_sec": 2.64,
    "segment_count": 6
  },
  "spectral_centroid": {
    "mean": 2021.17
  },
  "timeseries": {
    "frame_sec": 0.5,
    "pitch": [
      492.0,
      338.3,
      374.36,
      320.23,
      326.0,
      371.27,
      207.28,
      438.15,
      198.92,
      247.54,
      312.38,
      184.16,
      287.71,
      277.54,
      614.82,
      520.77,
      594.15,
      379.21,
      767.66,
      475.18,
      419.21,
      140.6,
      378.55,
      794.22,
      881.37,
      672.32,
      576.49,
      494.34,
      407.51,
      270.85
    ],
    "energy": [
      0.086121,
      0.043328,
      0.04354,
      0.02754,
      0.028465,
      0.027137,
      0.017741,
      0.013034,
      0.016546,
      0.034785,
      0.053172,
      0.029623,
      0.032695,
      0.066182,
      0.105757,
      0.078962,
      0.051802,
      0.05973,
      0.016332,
      0.01916,
      0.021051,
      0.01959,
      0.056235,
      0.156661,
      0.164621,
      0.083353,
      0.029112,
      0.048061,
      0.101717,
      0.049102
    ],
    "spectral_centroid": [
      1634.36,
      1788.48,
      2329.26,
      2239.46,
      1736.06,
      2250.38,
      2306.22,
      2063.11,
      2073.09,
      2262.41,
      2153.01,
      2023.48,
      2242.05,
      1923.38,
      1767.01,
      1866.1,
      1887.87,
      1742.49,
      2171.41,
      2253.94,
      2295.97,
      2066.9,
      2194.15,
      1773.76,
      1958.37,
      1760.59,
      2179.82,
      2065.23,
      1580.79,
      2103.17
    ]
  }
}