{
  "id": "24c92424-046c-476e-af30-91db9a56e14b",
  "duration": 8.107,
  "pitch": {
    "mean": 390.75,
    "max": 1673.01,
    "std": 206.02,
    "max_mean_ratio": 4.28
  },
  "energy": {
    "mean": 0.059142,
    "max": 0.122097,
    "std": 0.029998,
    "rate_of_change": 0.014711
  },
  "speech_rate": {
    "chars_per_sec": 13.99,
    "words_per_sec": 2.72,
    "segment_count": 1
  },
  "spectral_centroid": {
    "mean": 1718.15
  },
  "timeseries": {
    "frame_sec": 0.5,
    "pitch": [
      339.87,
      599.95,
      379.29,
      495.22,
      303.09,
      396.99,
      388.11,
      452.33,
      245.13,
      119.55,
      414.14,
      405.8,
      450.3,
      364.54,
      402.72,
      432.92,
      397.36
    ],
    "energy": [
      0.039123,
      0.058004,
      0.053577,
      0.056159,
      0.007513,
      0.080957,
      0.061869,
      0.065812,
      0.016335,
      0.015413,
      0.089883,
      0.086205,
      0.06324,
      0.064441,
      0.080825,
      0.066632,
      0.042676
    ],
    "spectral_centroid": [
      1801.35,
      1026.78,
      1756.87,
      1538.17,
      1781.35,
      1377.89,
      1867.55,
      1337.86,
      1557.45,
      1995.76,
      1683.81,
      2054.6,
      1930.75,
      2678.45,
      1963.45,
      1298.9,
      1539.43
    ]
  }
}