{
  "id": "2b8a2be6-233e-4d2a-af84-abdd780a1c97",
  "duration": 13.163,
  "pitch": {
    "mean": 300.21,
    "max": 1050.39,
    "std": 207.75,
    "max_mean_ratio": 3.5
  },
  "energy": {
    "mean": 0.043072,
    "max": 0.12427,
    "std": 0.019598,
    "rate_of_change": 0.008708
  },
  "speech_rate": {
    "chars_per_sec": 12.42,
    "words_per_sec": 2.44,
    "segment_count": 5
  },
  "spectral_centroid": {
    "mean": 2045.13
  },
  "timeseries": {
    "frame_sec": 0.5,
    "pitch": [
      354.62,
      243.15,
      386.35,
      281.66,
      331.7,
      243.73,
      216.04,
      193.72,
      357.42,
      240.59,
      184.92,
      327.64,
      157.61,
      274.64,
      281.2,
      468.15,
      355.5,
      306.04,
      183.03,
      290.03,
      436.36,
      397.96,
      199.19,
      517.12,
      206.01,
      315.37,
      180.15
    ],
    "energy": [
      0.039224,
      0.024935,
      0.046505,
      0.031311,
      0.042026,
      0.062942,
      0.040853,
      0.033243,
      0.039844,
      0.042941,
      0.030683,
      0.026438,
      0.020769,
      0.049702,
      0.042358,
      0.057104,
      0.030063,
      0.040346,
      0.037112,
      0.045177,
      0.045505,
      0.051272,
      0.051792,
      0.062052,
      0.019924,
      0.056338,
      0.029486
    ],
    "spectral_centroid": [
      2241.89,
      1920.21,
      2261.99,
      1982.28,
      1963.38,
      2089.72,
      1888.21,
      2416.58,
      2218.06,
      1779.06,
      1786.71,
      1905.93,
      2019.39,
      2048.85,
      2279.88,
      1829.07,
      1929.95,
      1889.5,
      2038.33,
      1987.87,
      1922.55,
      1789.79,
      2380.55,
      2148.2,
      2262.57,
      2005.6,
      2492.34
    ]
  }
}