{
  "id": "38579a58-b5cc-4c5d-adc9-93b8dbfc7238",
  "duration": 13.056,
  "pitch": {
    "mean": 579.7,
    "max": 2054.98,
    "std": 463.64,
    "max_mean_ratio": 3.54
  },
  "energy": {
    "mean": 0.067083,
    "max": 0.264668,
    "std": 0.053435,
    "rate_of_change": 0.019877
  },
  "speech_rate": {
    "chars_per_sec": 14.08,
    "words_per_sec": 2.13,
    "segment_count": 5
  },
  "spectral_centroid": {
    "mean": 1951.87
  },
  "timeseries": {
    "frame_sec": 0.5,
    "pitch": [
      804.45,
      668.34,
      660.73,
      620.61,
      349.48,
      369.8,
      337.76,
      407.22,
      785.77,
      682.7,
      747.85,
      382.87,
      777.11,
      577.15,
      398.68,
      652.14,
      583.89,
      273.43,
      302.54,
      320.25,
      677.7,
      1249.63,
      752.76,
      512.21,
      503.74,
      640.62,
      1101.55
    ],
    "energy": [
      0.085188,
      0.047767,
      0.070282,
      0.053659,
      0.022493,
      0.011536,
      0.008992,
      0.049582,
      0.128669,
      0.100087,
      0.072276,
      0.033732,
      0.103101,
      0.016006,
      0.049144,
      0.074908,
      0.076078,
      0.02426,
      0.032948,
      0.06136,
      0.153961,
      0.063677,
      0.049475,
      0.105041,
      0.068404,
      0.089989,
      0.093432
    ],
    "spectral_centroid": [
      1960.09,
      2089.44,
      2098.04,
      1708.51,
      1650.36,
      1945.83,
      2259.2,
      2011.77,
      1740.32,
      1960.58,
      1382.9,
      2078.79,
      1535.28,
      2047.48,
      2397.68,
      1634.97,
      1658.56,
      1973.03,
      1847.13,
      2395.58,
      2051.37,
      1961.03,
      2097.03,
      2312.36,
      2422.27,
      1739.59,
      1677.72
    ]
  }
}