{
  "id": "43c1626d-cc56-44a0-8d08-fe7927dcde43",
  "duration": 12.309,
  "pitch": {
    "mean": 380.61,
    "max": 1493.06,
    "std": 273.7,
    "max_mean_ratio": 3.92
  },
  "energy": {
    "mean": 0.053885,
    "max": 0.134466,
    "std": 0.033421,
    "rate_of_change": 0.010226
  },
  "speech_rate": {
    "chars_per_sec": 10.65,
    "words_per_sec": 1.79,
    "segment_count": 3
  },
  "spectral_centroid": {
    "mean": 2039.47
  },
  "timeseries": {
    "frame_sec": 0.5,
    "pitch": [
      468.89,
      574.18,
      439.73,
      327.39,
      544.88,
      703.54,
      577.27,
      230.29,
      165.54,
      328.59,
      461.43,
      499.41,
      133.81,
      142.52,
      161.64,
      146.43,
      287.77,
      315.33,
      477.98,
      409.89,
      569.43,
      270.21,
      394.73,
      565.45,
      147.04
    ],
    "energy": [
      0.056612,
      0.055438,
      0.053186,
      0.042843,
      0.066177,
      0.076503,
      0.081204,
      0.024869,
      0.016032,
      0.044811,
      0.051645,
      0.061341,
      0.015363,
      0.014339,
      0.023989,
      0.016463,
      0.105536,
      0.055379,
      0.074084,
      0.059967,
      0.068844,
      0.062268,
      0.082504,
      0.056855,
      0.012145
    ],
    "spectral_centroid": [
      2006.92,
      1693.02,
      1691.61,
      2353.53,
      2538.37,
      2674.16,
      2284.63,
      1736.04,
      1540.4,
      2186.85,
      2323.04,
      1984.61,
      1921.78,
      1438.48,
      1785.85,
      1994.06,
      1218.24,
      2103.81,
      2235.4,
      2154.73,
      2329.79,
      2343.42,
      2195.51,
      2169.75,
      2198.9
    ]
  }
}