{
  "id": "4c268406-3d63-46be-95eb-2764772d9766",
  "duration": 13.995,
  "pitch": {
    "mean": 357.85,
    "max": 1778.83,
    "std": 193.01,
    "max_mean_ratio": 4.97
  },
  "energy": {
    "mean": 0.004343,
    "max": 0.016579,
    "std": 0.003484,
    "rate_of_change": 0.001167
  },
  "speech_rate": {
    "chars_per_sec": 14.72,
    "words_per_sec": 2.66,
    "segment_count": 4
  },
  "spectral_centroid": {
    "mean": 1691.23
  },
  "timeseries": {
    "frame_sec": 0.5,
    "pitch": [
      351.08,
      221.47,
      274.63,
      263.01,
      358.4,
      413.35,
      470.32,
      238.91,
      334.68,
      386.98,
      367.73,
      386.43,
      326.49,
      221.4,
      303.9,
      406.68,
      490.59,
      257.97,
      558.66,
      294.24,
      362.22,
      344.53,
      403.02,
      435.76,
      369.43,
      531.71,
      270.54,
      263.73
    ],
    "energy": [
      0.001194,
      0.003163,
      0.004586,
      0.005559,
      0.008141,
      0.00162,
      0.00115,
      0.000853,
      0.001219,
      0.009709,
      0.009501,
      0.007339,
      0.006329,
      0.003482,
      0.004172,
      0.003623,
      0.001137,
      0.000784,
      0.001297,
      0.002119,
      0.007041,
      0.005755,
      0.006643,
      0.004092,
      0.007742,
      0.004024,
      0.00282,
      0.001337
    ],
    "spectral_centroid": [
      2109.32,
      1680.03,
      1569.52,
      1843.75,
      1695.97,
      2022.09,
      1781.09,
      2151.52,
      2055.22,
      1611.4,
      1957.81,
      1524.25,
      1481.72,
      1263.62,
      1152.85,
      1278.18,
      1789.26,
      2156.29,
      1499.72,
      2032.36,
      1757.29,
      1606.92,
      1333.12,
      1552.17,
      1232.98,
      1806.67,
      1590.03,
      1831.87
    ]
  }
}