{
  "id": "5b6a44db-b57a-4495-a75d-55972b0cfbb8",
  "duration": 13.163,
  "pitch": {
    "mean": 258.23,
    "max": 1325.43,
    "std": 207.73,
    "max_mean_ratio": 5.13
  },
  "energy": {
    "mean": 0.083696,
    "max": 0.233399,
    "std": 0.050044,
    "rate_of_change": 0.016143
  },
  "speech_rate": {
    "chars_per_sec": 9.47,
    "words_per_sec": 1.38,
    "segment_count": 3
  },
  "spectral_centroid": {
    "mean": 1780.19
  },
  "timeseries": {
    "frame_sec": 0.5,
    "pitch": [
      156.01,
      261.08,
      465.63,
      232.91,
      226.95,
      305.17,
      203.31,
      242.26,
      369.76,
      444.16,
      182.69,
      198.54,
      214.97,
      160.62,
      245.32,
      374.5,
      223.67,
      284.26,
      270.72,
      214.76,
      358.88,
      238.45,
      191.24,
      337.41,
      336.17,
      177.43,
      195.74
    ],
    "energy": [
      0.031646,
      0.085041,
      0.089175,
      0.082741,
      0.025268,
      0.052776,
      0.04735,
      0.136066,
      0.03292,
      0.048865,
      0.115708,
      0.090321,
      0.029687,
      0.108079,
      0.075163,
      0.11763,
      0.127855,
      0.133851,
      0.123097,
      0.066068,
      0.084696,
      0.04283,
      0.055692,
      0.121765,
      0.117888,
      0.046328,
      0.048882
    ],
    "spectral_centroid": [
      1825.95,
      1720.97,
      1491.87,
      1477.41,
      1772.45,
      1737.29,
      1597.72,
      1994.93,
      2105.92,
      1478.9,
      1240.05,
      1667.22,
      1722.24,
      1793.42,
      1703.59,
      1865.64,
      2132.85,
      1648.69,
      1449.7,
      1726.74,
      1439.79,
      2020.24,
      2203.91,
      2203.1,
      1992.7,
      2164.12,
      2054.16
    ]
  }
}