{
  "id": "7f7bf8d1-7712-4c49-99f8-7324b8fc2c23",
  "duration": 9.792,
  "pitch": {
    "mean": 446.01,
    "max": 1747.11,
    "std": 276.74,
    "max_mean_ratio": 3.92
  },
  "energy": {
    "mean": 0.089062,
    "max": 0.231946,
    "std": 0.06596,
    "rate_of_change": 0.023188
  },
  "speech_rate": {
    "chars_per_sec": 5.52,
    "words_per_sec": 0.92,
    "segment_count": 2
  },
  "spectral_centroid": {
    "mean": 1996.35
  },
  "timeseries": {
    "frame_sec": 0.5,
    "pitch": [
      427.06,
      429.13,
      442.74,
      329.08,
      457.1,
      450.56,
      363.65,
      432.0,
      368.92,
      509.51,
      352.7,
      276.79,
      285.77,
      158.53,
      262.42,
      593.57,
      699.22,
      678.55,
      678.02,
      641.98
    ],
    "energy": [
      0.116289,
      0.096688,
      0.102189,
      0.085228,
      0.119493,
      0.091854,
      0.074898,
      0.106542,
      0.100915,
      0.139496,
      0.016927,
      0.008583,
      0.014695,
      0.013066,
      0.009189,
      0.040511,
      0.126201,
      0.165638,
      0.142977,
      0.161222
    ],
    "spectral_centroid": [
      1717.52,
      1410.36,
      1777.06,
      1945.72,
      1828.9,
      2370.23,
      2245.09,
      1952.0,
      2066.4,
      1459.75,
      2159.02,
      2491.31,
      2144.5,
      2171.17,
      2447.42,
      1938.93,
      1682.72,
      2233.84,
      1973.35,
      1620.06
    ]
  }
}