{
  "id": "9c439c0f-19a1-4fac-b25c-ed640ee41c79",
  "duration": 11.669,
  "pitch": {
    "mean": 463.53,
    "max": 1817.19,
    "std": 282.69,
    "max_mean_ratio": 3.92
  },
  "energy": {
    "mean": 0.02524,
    "max": 0.084326,
    "std": 0.012643,
    "rate_of_change": 0.006723
  },
  "speech_rate": {
    "chars_per_sec": 25.09,
    "words_per_sec": 4.85,
    "segment_count": 5
  },
  "spectral_centroid": {
    "mean": 1712.09
  },
  "timeseries": {
    "frame_sec": 0.5,
    "pitch": [
      484.42,
      342.86,
      406.2,
      805.45,
      406.23,
      468.1,
      470.88,
      305.91,
      291.04,
      442.13,
      473.33,
      494.85,
      383.26,
      247.59,
      422.47,
      533.96,
      416.78,
      681.44,
      559.97,
      590.95,
      569.25,
      437.55,
      450.61,
      347.14
    ],
    "energy": [
      0.013873,
      0.015903,
      0.024126,
      0.033328,
      0.014418,
      0.016097,
      0.018879,
      0.024782,
      0.023662,
      0.030623,
      0.024327,
      0.019563,
      0.018548,
      0.013951,
      0.017867,
      0.026842,
      0.027369,
      0.023888,
      0.031792,
      0.038968,
      0.028762,
      0.023495,
      0.042703,
      0.014884
    ],
    "spectral_centroid": [
      1566.72,
      1976.24,
      2225.7,
      1584.6,
      1767.99,
      1605.44,
      1561.23,
      1701.36,
      2168.38,
      1799.22,
      1668.84,
      1565.15,
      1681.31,
      1584.57,
      1511.35,
      1715.84,
      1552.45,
      1720.66,
      1698.45,
      1602.22,
      1516.85,
      1780.0,
      1769.82,
      1936.59
    ]
  }
}