{
  "id": "a49fcf52-f713-4f5c-9951-7eedc21e4460",
  "duration": 11.989,
  "pitch": {
    "mean": 384.98,
    "max": 1857.65,
    "std": 332.07,
    "max_mean_ratio": 4.83
  },
  "energy": {
    "mean": 0.04489,
    "max": 0.386994,
    "std": 0.073564,
    "rate_of_change": 0.031833
  },
  "speech_rate": {
    "chars_per_sec": 9.53,
    "words_per_sec": 1.71,
    "segment_count": 4
  },
  "spectral_centroid": {
    "mean": 1859.03
  },
  "timeseries": {
    "frame_sec": 0.5,
    "pitch": [
      257.7,
      249.01,
      424.21,
      121.82,
      216.19,
      435.14,
      263.32,
      365.4,
      412.47,
      304.39,
      236.77,
      135.16,
      288.59,
      324.86,
      437.04,
      247.15,
      335.23,
      427.47,
      336.78,
      946.54,
      690.04,
      581.37,
      650.94,
      551.38
    ],
    "energy": [
      0.006743,
      0.030201,
      0.045493,
      0.01235,
      0.017717,
      0.048098,
      0.007126,
      0.026644,
      0.041243,
      0.033688,
      0.01234,
      0.007583,
      0.007286,
      0.006547,
      0.019653,
      0.02725,
      0.025923,
      0.022678,
      0.010299,
      0.0227,
      0.286205,
      0.201113,
      0.089785,
      0.022271
    ],
    "spectral_centroid": [
      1909.25,
      1693.66,
      1691.14,
      1729.55,
      1906.4,
      1885.06,
      1709.39,
      1650.63,
      1728.04,
      1771.36,
      2076.02,
      1774.35,
      1692.72,
      1836.87,
      1710.21,
      1676.08,
      1703.54,
      1890.0,
      2030.5,
      2287.03,
      2028.81,
      2121.21,
      2259.92,
      1848.92
    ]
  }
}