{
  "id": "acab2480-f589-4643-a59a-f1894a1617e0",
  "duration": 8.853,
  "pitch": {
    "mean": 535.25,
    "max": 1968.41,
    "std": 437.32,
    "max_mean_ratio": 3.68
  },
  "energy": {
    "mean": 0.096591,
    "max": 0.359048,
    "std": 0.077951,
    "rate_of_change": 0.03929
  },
  "speech_rate": {
    "chars_per_sec": 15.17,
    "words_per_sec": 2.61,
    "segment_count": 5
  },
  "spectral_centroid": {
    "mean": 2102.85
  },
  "timeseries": {
    "frame_sec": 0.5,
    "pitch": [
      817.07,
      361.86,
      738.38,
      422.81,
      311.71,
      203.52,
      427.63,
      542.14,
      724.06,
      241.95,
      782.56,
      134.41,
      467.82,
      599.0,
      696.65,
      751.91,
      851.18,
      653.18
    ],
    "energy": [
      0.100377,
      0.046139,
      0.126682,
      0.04861,
      0.05445,
      0.031953,
      0.029777,
      0.100206,
      0.176579,
      0.051376,
      0.117493,
      0.011998,
      0.099685,
      0.09091,
      0.14628,
      0.183164,
      0.151207,
      0.099657
    ],
    "spectral_centroid": [
      1896.15,
      2128.11,
      2336.64,
      1978.3,
      1811.97,
      1858.08,
      2064.93,
      1859.62,
      1998.62,
      2814.3,
      1900.06,
      2394.88,
      1953.52,
      2490.03,
      1977.27,
      1998.2,
      2360.65,
      2047.42
    ]
  }
}