{
  "id": "b50edb66-a516-4c6c-bb26-97035728d775",
  "duration": 14.187,
  "pitch": {
    "mean": 597.41,
    "max": 1870.44,
    "std": 315.51,
    "max_mean_ratio": 3.13
  },
  "energy": {
    "mean": 0.080634,
    "max": 0.264769,
    "std": 0.061034,
    "rate_of_change": 0.018217
  },
  "speech_rate": {
    "chars_per_sec": 13.63,
    "words_per_sec": 2.68,
    "segment_count": 3
  },
  "spectral_centroid": {
    "mean": 1953.94
  },
  "timeseries": {
    "frame_sec": 0.5,
    "pitch": [
      424.55,
      462.81,
      258.34,
      494.12,
      387.26,
      412.03,
      660.5,
      602.58,
      978.19,
      607.77,
      430.77,
      367.78,
      333.37,
      447.35,
      365.27,
      482.19,
      413.26,
      818.78,
      914.49,
      845.75,
      556.1,
      928.44,
      1014.09,
      583.98,
      788.21,
      722.15,
      658.68,
      639.37,
      711.56
    ],
    "energy": [
      0.045416,
      0.070379,
      0.027635,
      0.066804,
      0.037997,
      0.042028,
      0.104584,
      0.074299,
      0.096705,
      0.064208,
      0.082847,
      0.039632,
      0.030034,
      0.052047,
      0.061197,
      0.048444,
      0.05946,
      0.149574,
      0.169759,
      0.021104,
      0.093695,
      0.166633,
      0.196752,
      0.121582,
      0.110994,
      0.10344,
      0.023835,
      0.021753,
      0.018866
    ],
    "spectral_centroid": [
      1945.65,
      1993.14,
      1807.94,
      1681.91,
      2569.92,
      1809.21,
      1812.74,
      2382.61,
      2009.58,
      2168.18,
      1836.21,
      1927.34,
      2012.64,
      1900.37,
      1758.45,
      1961.48,
      2022.23,
      1892.59,
      1785.01,
      1728.82,
      1827.64,
      2008.7,
      2093.39,
      1669.22,
      2089.33,
      2198.56,
      1990.16,
      1817.53,
      1833.63
    ]
  }
}