{
  "id": "b7469601-82f7-4e21-93ec-49ca371da60b",
  "duration": 10.112,
  "pitch": {
    "mean": 384.29,
    "max": 1568.27,
    "std": 250.88,
    "max_mean_ratio": 4.08
  },
  "energy": {
    "mean": 0.042603,
    "max": 0.106082,
    "std": 0.027282,
    "rate_of_change": 0.010083
  },
  "speech_rate": {
    "chars_per_sec": 13.86,
    "words_per_sec": 2.28,
    "segment_count": 4
  },
  "spectral_centroid": {
    "mean": 1817.55
  },
  "timeseries": {
    "frame_sec": 0.5,
    "pitch": [
      484.03,
      424.56,
      529.26,
      553.49,
      426.55,
      421.47,
      445.17,
      312.95,
      453.47,
      370.85,
      417.36,
      549.66,
      495.3,
      628.85,
      216.06,
      165.79,
      114.38,
      175.75,
      348.43,
      454.22,
      351.89
    ],
    "energy": [
      0.060818,
      0.044755,
      0.064965,
      0.046386,
      0.057663,
      0.041163,
      0.050351,
      0.007672,
      0.007243,
      0.050083,
      0.046226,
      0.064067,
      0.047962,
      0.071627,
      0.009585,
      0.007851,
      0.013745,
      0.022706,
      0.034073,
      0.069191,
      0.032063
    ],
    "spectral_centroid": [
      1595.16,
      1910.01,
      1609.51,
      1710.99,
      2295.81,
      1641.71,
      1780.36,
      1976.77,
      1705.86,
      2052.72,
      2225.43,
      1517.83,
      1412.75,
      1726.49,
      1889.33,
      1815.05,
      1949.85,
      1960.37,
      1893.54,
      1474.53,
      2731.97
    ]
  }
}