{
  "id": "c7484242-6128-4725-8246-68a9be8f9e65",
  "duration": 10.347,
  "pitch": {
    "mean": 344.37,
    "max": 1103.21,
    "std": 216.89,
    "max_mean_ratio": 3.2
  },
  "energy": {
    "mean": 0.04809,
    "max": 0.141166,
    "std": 0.028201,
    "rate_of_change": 0.013032
  },
  "speech_rate": {
    "chars_per_sec": 14.63,
    "words_per_sec": 2.52,
    "segment_count": 2
  },
  "spectral_centroid": {
    "mean": 1871.26
  },
  "timeseries": {
    "frame_sec": 0.5,
    "pitch": [
      456.11,
      433.37,
      374.39,
      586.34,
      264.46,
      389.77,
      344.81,
      369.64,
      386.1,
      392.57,
      478.07,
      478.06,
      285.79,
      293.02,
      443.41,
      199.49,
      159.18,
      152.47,
      116.83,
      159.54,
      571.88
    ],
    "energy": [
      0.05162,
      0.052577,
      0.064199,
      0.053527,
      0.034318,
      0.063317,
      0.058013,
      0.060575,
      0.047214,
      0.043021,
      0.056069,
      0.070243,
      0.051265,
      0.051197,
      0.049283,
      0.024298,
      0.00686,
      0.011211,
      0.017882,
      0.01353,
      0.098449
    ],
    "spectral_centroid": [
      1569.45,
      1924.65,
      2335.77,
      1370.0,
      1719.04,
      1971.96,
      2565.14,
      1585.66,
      1982.72,
      1708.35,
      1648.05,
      1727.83,
      1995.25,
      2317.64,
      1766.19,
      1594.64,
      1606.78,
      1807.91,
      2227.91,
      2269.79,
      1628.48
    ]
  }
}