{
  "id": "e25f539c-4930-49e5-849e-ffc671f7e4b9",
  "duration": 6.059,
  "pitch": {
    "mean": 486.84,
    "max": 2069.25,
    "std": 330.72,
    "max_mean_ratio": 4.25
  },
  "energy": {
    "mean": 0.072642,
    "max": 0.14862,
    "std": 0.028217,
    "rate_of_change": 0.021299
  },
  "speech_rate": {
    "chars_per_sec": 27.76,
    "words_per_sec": 5.69,
    "segment_count": 3
  },
  "spectral_centroid": {
    "mean": 2101.69
  },
  "timeseries": {
    "frame_sec": 0.5,
    "pitch": [
      268.94,
      405.01,
      356.04,
      412.36,
      429.58,
      279.04,
      425.9,
      492.35,
      493.48,
      753.24,
      633.1,
      802.59,
      594.26
    ],
    "energy": [
      0.057455,
      0.055995,
      0.047651,
      0.065827,
      0.051389,
      0.06492,
      0.074229,
      0.085468,
      0.090257,
      0.081449,
      0.076835,
      0.087612,
      0.057824
    ],
    "spectral_centroid": [
      2157.72,
      2182.84,
      1922.87,
      2361.44,
      2272.72,
      2088.45,
      1783.7,
      1951.39,
      1835.87,
      2247.55,
      2163.16,
      2175.59,
      2655.04
    ]
  }
}