{
  "id": "f8bbe6a8-b848-4893-ba4c-a59b8ae51005",
  "duration": 11.968,
  "pitch": {
    "mean": 549.95,
    "max": 1957.08,
    "std": 409.68,
    "max_mean_ratio": 3.56
  },
  "energy": {
    "mean": 0.045001,
    "max": 0.226695,
    "std": 0.055642,
    "rate_of_change": 0.018582
  },
  "speech_rate": {
    "chars_per_sec": 13.75,
    "words_per_sec": 2.68,
    "segment_count": 2
  },
  "spectral_centroid": {
    "mean": 1917.08
  },
  "timeseries": {
    "frame_sec": 0.5,
    "pitch": [
      370.44,
      465.1,
      521.58,
      258.41,
      380.2,
      411.42,
      554.75,
      597.03,
      843.15,
      475.88,
      555.88,
      401.88,
      425.81,
      359.78,
      272.04,
      562.35,
      809.68,
      740.43,
      1268.08,
      1093.51,
      277.94,
      582.52,
      560.56,
      496.97
    ],
    "energy": [
      0.017535,
      0.01537,
      0.039526,
      0.021256,
      0.022427,
      0.019587,
      0.016372,
      0.018258,
      0.021826,
      0.01636,
      0.012209,
      0.019631,
      0.016077,
      0.018553,
      0.023673,
      0.084889,
      0.160184,
      0.175989,
      0.163464,
      0.052581,
      0.014781,
      0.022226,
      0.021177,
      0.039782
    ],
    "spectral_centroid": [
      2129.23,
      2080.2,
      1904.14,
      1916.74,
      1714.78,
      1799.0,
      1779.23,
      1906.16,
      1680.25,
      2049.59,
      2007.49,
      1616.79,
      1829.52,
      1656.93,
      2014.84,
      1866.1,
      1841.14,
      2227.86,
      2126.83,
      2090.98,
      2121.98,
      1856.83,
      2037.5,
      1799.96
    ]
  }
}